[
  {
    "id": "AO-001",
    "room_id": "AO-001",
    "name": "BIT Lecture Lab Room 5",
    "type": "facility",
    "svgId": "BIT Lecture Lab Room 5",
    "svg_id": "BIT Lecture Lab Room 5",
    "buildingId": null,
    "floor": null,
    "floors": null,
    "category": "Facility",
    "description": "BIT Lecture Lab Room 5.",
    "image": "/images/facilities/BITLectureLab5.JPG",
    "keywords": [
      "ao-001",
      "bit lecture lab room 5",
      "standalone"
    ],
    "x": 1018.25,
    "y": 784.59
  },
  {
    "id": "AO-002",
    "room_id": "AO-002",
    "name": "GT Lab 3",
    "type": "facility",
    "svgId": "GT Lab 3",
    "svg_id": "GT Lab 3",
    "buildingId": null,
    "floor": null,
    "floors": null,
    "category": "Facility",
    "description": "GT Lab 3.",
    "image": "/images/facilities/GTLab3.JPG",
    "keywords": [
      "ao-002",
      "gt lab 3",
      "standalone"
    ],
    "x": 1018.25,
    "y": 754.59
  },
  {
    "id": "AO-003",
    "room_id": "AO-003",
    "name": "DT Lab 1",
    "type": "facility",
    "svgId": "DT Lab 1",
    "svg_id": "DT Lab 1",
    "buildingId": null,
    "floor": null,
    "floors": null,
    "category": "Facility",
    "description": "DT Lab 1.",
    "image": "/images/facilities/DTLab1&2.JPG",
    "keywords": [
      "ao-003",
      "dt lab 1",
      "standalone"
    ],
    "x": 1018.25,
    "y": 724.59
  },
  {
    "id": "AO-004",
    "room_id": "AO-004",
    "name": "DT Lab 2",
    "type": "facility",
    "svgId": "DT Lab 2",
    "svg_id": "DT Lab 2",
    "buildingId": null,
    "floor": null,
    "floors": null,
    "category": "Facility",
    "description": "DT Lab 2.",
    "image": "/images/facilities/DTLab1&2.JPG",
    "keywords": [
      "ao-004",
      "dt lab 2",
      "standalone"
    ],
    "x": 1018.25,
    "y": 694.59
  },
  {
    "id": "AO-005",
    "room_id": "AO-005",
    "name": "ES Room 3",
    "type": "facility",
    "svgId": "ES Room 3",
    "svg_id": "ES Room 3",
    "buildingId": null,
    "floor": null,
    "floors": null,
    "category": "Facility",
    "description": "ES Room 3.",
    "image": "/images/facilities/ESRoom3.JPG",
    "keywords": [
      "ao-005",
      "es room 3",
      "standalone"
    ],
    "x": 947,
    "y": 715
  },
  {
    "id": "AO-006",
    "room_id": "AO-006",
    "name": "ES Room 2",
    "type": "facility",
    "svgId": "ES Room 2",
    "svg_id": "ES Room 2",
    "buildingId": null,
    "floor": null,
    "floors": null,
    "category": "Facility",
    "description": "ES Room 2.",
    "image": "/images/facilities/ESRoom2.JPG",
    "keywords": [
      "ao-006",
      "es room 2",
      "standalone"
    ],
    "x": 919,
    "y": 715
  },
  {
    "id": "AO-007",
    "room_id": "AO-007",
    "name": "ES Room 1",
    "type": "facility",
    "svgId": "ES Room 1",
    "svg_id": "ES Room 1",
    "buildingId": null,
    "floor": null,
    "floors": null,
    "category": "Facility",
    "description": "ES Room 1.",
    "image": "/images/facilities/ESRoom1.JPG",
    "keywords": [
      "ao-007",
      "es room 1",
      "standalone"
    ],
    "x": 891,
    "y": 715
  },
  {
    "id": "AO-010",
    "room_id": "AO-010",
    "name": "BIT AT Lab 1",
    "type": "facility",
    "svgId": "BIT AT Lab 1",
    "svg_id": "BIT AT Lab 1",
    "buildingId": null,
    "floor": null,
    "floors": null,
    "category": "Facility",
    "description": "BIT AT Lab 1.",
    "image": "/images/facilities/BITATLab1.JPG",
    "keywords": [
      "ao-010",
      "bit at lab 1",
      "standalone"
    ],
    "x": 955.34,
    "y": 567.84
  },
  {
    "id": "AO-011",
    "room_id": "AO-011",
    "name": "BIT AT Lab 2",
    "type": "facility",
    "svgId": "BIT AT Lab 2",
    "svg_id": "BIT AT Lab 2",
    "buildingId": null,
    "floor": null,
    "floors": null,
    "category": "Facility",
    "description": "BIT AT Lab 2.",
    "image": "/images/facilities/BITATLab2.JPG",
    "keywords": [
      "ao-011",
      "bit at lab 2",
      "standalone"
    ],
    "x": 951.56,
    "y": 537.42
  },
  {
    "id": "AO-012",
    "room_id": "AO-012",
    "name": "BIT AT Lab 3",
    "type": "facility",
    "svgId": "BIT AT Lab 3",
    "svg_id": "BIT AT Lab 3",
    "buildingId": null,
    "floor": null,
    "floors": null,
    "category": "Facility",
    "description": "BIT AT Lab 3.",
    "image": "/images/facilities/BITATLab3.JPG",
    "keywords": [
      "ao-012",
      "bit at lab 3",
      "standalone"
    ],
    "x": 947.56,
    "y": 507.42
  },
  {
    "id": "AO-013",
    "room_id": "AO-013",
    "name": "BIT AT Lab 4",
    "type": "facility",
    "svgId": "BIT AT Lab 4",
    "svg_id": "BIT AT Lab 4",
    "buildingId": null,
    "floor": null,
    "floors": null,
    "category": "Facility",
    "description": "BIT AT Lab 4.",
    "image": "/images/facilities/BITATLab4.JPG",
    "keywords": [
      "ao-013",
      "bit at lab 4",
      "standalone"
    ],
    "x": 943.56,
    "y": 477.42
  },
  {
    "id": "AO-015",
    "room_id": "AO-015",
    "name": "BENRC Tissue Culture Lab",
    "type": "facility",
    "svgId": "BENRC Tissue Culture Lab",
    "svg_id": "BENRC Tissue Culture Lab",
    "buildingId": null,
    "floor": null,
    "floors": null,
    "category": "Facility",
    "description": "BENRC Tissue Culture Lab.",
    "image": "/images/facilities/BENRCTissueCultureLab.JPG",
    "keywords": [
      "ao-015",
      "benrc tissue culture lab",
      "standalone"
    ],
    "x": 898.32,
    "y": 441.56
  },
  {
    "id": "AO-016",
    "room_id": "AO-016",
    "name": "BENRC-IFNI Training Center",
    "type": "facility",
    "svgId": "BENRC-IFNI Training Center",
    "svg_id": "BENRC-IFNI Training Center",
    "buildingId": null,
    "floor": null,
    "floors": null,
    "category": "Facility",
    "description": "BENRC-IFNI Training Center.",
    "image": "/images/facilities/BENRCIFNITrainingCenter.JPG",
    "keywords": [
      "ao-016",
      "benrc-ifni training center",
      "standalone"
    ],
    "x": 851.22,
    "y": 457.42
  },
  {
    "id": "AO-017",
    "room_id": "AO-017",
    "name": "BENRC Microtel",
    "type": "facility",
    "svgId": "BENRC Microtel",
    "svg_id": "BENRC Microtel",
    "buildingId": null,
    "floor": null,
    "floors": null,
    "category": "Facility",
    "description": "BENRC Microtel.",
    "image": "/images/facilities/BENRCMicrotel.JPG",
    "keywords": [
      "ao-017",
      "benrc microtel",
      "standalone"
    ],
    "x": 844.91,
    "y": 430.89
  },
  {
    "id": "AO-027",
    "room_id": "AO-027",
    "name": "GDS Lab",
    "type": "facility",
    "svgId": "GDS Lab",
    "svg_id": "GDS Lab",
    "buildingId": null,
    "floor": null,
    "floors": null,
    "category": "Facility",
    "description": "GDS Lab.",
    "image": "/images/facilities/GDSLab.JPG",
    "keywords": [
      "ao-027",
      "gds lab",
      "standalone"
    ],
    "x": 666.5,
    "y": 853.5
  },
  {
    "id": "AO-029",
    "room_id": "AO-029",
    "name": "Power House",
    "type": "facility",
    "svgId": "Power House",
    "svg_id": "Power House",
    "buildingId": null,
    "floor": null,
    "floors": null,
    "category": "Facility",
    "description": "Power House.",
    "image": "/images/facilities/PowerHouse.JPG",
    "keywords": [
      "ao-029",
      "power house",
      "standalone"
    ],
    "x": 666.5,
    "y": 803
  },
  {
    "id": "AO-030",
    "room_id": "AO-030",
    "name": "General Services",
    "type": "facility",
    "svgId": "General Services",
    "svg_id": "General Services",
    "buildingId": null,
    "floor": null,
    "floors": null,
    "category": "Facility",
    "description": "General Services.",
    "image": "/images/facilities/GeneralServices.JPG",
    "keywords": [
      "ao-030",
      "general services",
      "standalone"
    ],
    "x": 674.5,
    "y": 778
  },
  {
    "id": "AO-031",
    "room_id": "AO-031",
    "name": "Maintenance",
    "type": "facility",
    "svgId": "Maintenance",
    "svg_id": "Maintenance",
    "buildingId": null,
    "floor": null,
    "floors": null,
    "category": "Facility",
    "description": "Maintenance.",
    "image": "/images/facilities/MaintenanceSR.JPG",
    "keywords": [
      "ao-031",
      "maintenance",
      "standalone"
    ],
    "x": 636.5,
    "y": 853
  },
  {
    "id": "AO-033",
    "room_id": "AO-033",
    "name": "Storage Room",
    "type": "facility",
    "svgId": "Storage Room",
    "svg_id": "Storage Room",
    "buildingId": null,
    "floor": null,
    "floors": null,
    "category": "Facility",
    "description": "Storage Room.",
    "image": "/images/facilities/StorageRoom.JPG",
    "keywords": [
      "ao-033",
      "storage room",
      "standalone"
    ],
    "x": 613.5,
    "y": 847.5
  },
  {
    "id": "AO-035",
    "room_id": "AO-035",
    "name": "Southern Ripples",
    "type": "facility",
    "svgId": "Southern Ripples",
    "svg_id": "Southern Ripples",
    "buildingId": null,
    "floor": null,
    "floors": null,
    "category": "Facility",
    "description": "Southern Ripples.",
    "image": "/images/facilities/SouthernRipples.JPG",
    "keywords": [
      "ao-035",
      "southern ripples",
      "standalone"
    ],
    "x": 612,
    "y": 868
  },
  {
    "id": "AO-043",
    "room_id": "AO-043",
    "name": "Kahimsug Center Sci-Tech Argao",
    "type": "facility",
    "svgId": "Kahimsug Center Sci-Tech Argao",
    "svg_id": "Kahimsug Center Sci-Tech Argao",
    "buildingId": null,
    "floor": null,
    "floors": null,
    "category": "Facility",
    "description": "Kahimsug Center Sci-Tech Argao.",
    "image": "/images/facilities/KahimsugCenter.JPG",
    "keywords": [
      "ao-043",
      "kahimsug center sci-tech argao",
      "standalone"
    ],
    "x": 656,
    "y": 1004
  },
  {
    "id": "AO-044",
    "room_id": "AO-044",
    "name": "Balay sa Alumni",
    "type": "facility",
    "svgId": "Balay sa Alumni",
    "svg_id": "Balay sa Alumni",
    "buildingId": null,
    "floor": null,
    "floors": null,
    "category": "Facility",
    "description": "Balay sa Alumni.",
    "image": "/images/facilities/BalaySaAlumni.JPG",
    "keywords": [
      "ao-044",
      "balay sa alumni",
      "standalone"
    ],
    "x": 678,
    "y": 1004
  },
  {
    "id": "AO-045",
    "room_id": "AO-045",
    "name": "Guard House",
    "type": "facility",
    "svgId": "Guard House",
    "svg_id": "Guard House",
    "buildingId": null,
    "floor": null,
    "floors": null,
    "category": "Facility",
    "description": "Guard House.",
    "image": "/images/facilities/GuardHouse.JPG",
    "keywords": [
      "ao-045",
      "guard house",
      "standalone"
    ],
    "x": 703,
    "y": 1001.5
  },
  {
    "id": "AO-046",
    "room_id": "AO-046",
    "name": "CTU-Argao Chess Center",
    "type": "facility",
    "svgId": "CTU-Argao Chess Center",
    "svg_id": "CTU-Argao Chess Center",
    "buildingId": null,
    "floor": null,
    "floors": null,
    "category": "Facility",
    "description": "CTU-Argao Chess Center.",
    "image": "/images/placeholders/default.svg",
    "keywords": [
      "ao-046",
      "ctu-argao chess center",
      "standalone"
    ],
    "x": 866.5,
    "y": 1014.5
  },
  {
    "id": "F-001",
    "room_id": "F-001",
    "name": "Student Lounge",
    "type": "facility",
    "svgId": "Student Lounge",
    "svg_id": "Student Lounge",
    "buildingId": null,
    "floor": null,
    "floors": null,
    "category": "Facility",
    "description": "Student Lounge.",
    "image": "/images/facilities/StudentLounge.JPG",
    "keywords": [
      "f-001",
      "student lounge"
    ],
    "x": 824.5,
    "y": 862.5
  },
  {
    "id": "F-002",
    "room_id": "F-002",
    "name": "Chapel",
    "type": "facility",
    "svgId": "Chapel",
    "svg_id": "Chapel",
    "buildingId": "B004",
    "floor": 1,
    "floors": null,
    "category": "Facility",
    "description": "Chapel.",
    "image": "/images/facilities/Chapel.JPG",
    "keywords": [
      "f-002",
      "chapel"
    ],
    "x": 904.5,
    "y": 820.5,
    "building_id": 4
  },
  {
    "id": "F-003",
    "room_id": "F-003",
    "name": "Canteen",
    "type": "facility",
    "svgId": "Canteen",
    "svg_id": "Canteen",
    "buildingId": null,
    "floor": null,
    "floors": null,
    "category": "Facility",
    "description": "Canteen.",
    "image": "/images/facilities/Canteen.JPG",
    "keywords": [
      "f-003",
      "canteen"
    ],
    "x": 775.33,
    "y": 801.55
  },
  {
    "id": "F-004",
    "room_id": "F-004",
    "name": "Basketball Court",
    "type": "facility",
    "svgId": "Basketball Court",
    "svg_id": "Basketball Court",
    "buildingId": null,
    "floor": null,
    "floors": null,
    "category": "Facility",
    "description": "Basketball Court.",
    "image": "/images/placeholders/default.svg",
    "keywords": [
      "f-004",
      "basketball court"
    ],
    "x": 749.5,
    "y": 873.5
  },
  {
    "id": "F-005",
    "room_id": "F-005",
    "name": "Kalampusan Gym",
    "type": "facility",
    "svgId": "Kalampusan Gym",
    "svg_id": "Kalampusan Gym",
    "buildingId": null,
    "floor": null,
    "floors": null,
    "category": "Facility",
    "description": "Kalampusan Gym.",
    "image": "/images/facilities/KalampusanGym.JPG",
    "keywords": [
      "f-005",
      "kalampusan gym"
    ],
    "x": 754.61,
    "y": 745.44
  },
  {
    "id": "F-006",
    "room_id": "F-006",
    "name": "Green House",
    "type": "facility",
    "svgId": "Green House",
    "svg_id": "Green House",
    "buildingId": null,
    "floor": null,
    "floors": null,
    "category": "Facility",
    "description": "Green House.",
    "image": "/images/facilities/GreenHouse.JPG",
    "keywords": [
      "f-006",
      "green house"
    ],
    "x": 795.05,
    "y": 215.18
  },
  {
    "id": "F-007",
    "room_id": "F-007",
    "name": "Old Stage",
    "type": "facility",
    "svgId": "Old Stage",
    "svg_id": "Old Stage",
    "buildingId": null,
    "floor": null,
    "floors": null,
    "category": "Facility",
    "description": "Old Stage.",
    "image": "/images/facilities/OldStage.JPG",
    "keywords": [
      "f-007",
      "old stage"
    ],
    "x": 854.5,
    "y": 575
  },
  {
    "id": "F-008",
    "room_id": "F-008",
    "name": "Oval",
    "type": "facility",
    "svgId": "Oval",
    "svg_id": "Oval",
    "buildingId": null,
    "floor": null,
    "floors": null,
    "category": "Facility",
    "description": "Oval.",
    "image": "/images/facilities/Oval.JPG",
    "keywords": [
      "f-008",
      "oval"
    ],
    "x": 742.64,
    "y": 570.5
  }
]
